isort/__init__.py
isort/__main__.py
isort/compat.py
isort/finders.py
isort/format.py
isort/hooks.py
isort/isort.py
isort/main.py
isort/natural.py
isort/pie_slice.py
isort/pylama_isort.py
isort/settings.py
isort/utils.py
isort/stdlibs/__init__.py
isort/stdlibs/py27.py
isort/stdlibs/py3.py
isort_black_compat-4.3.211.dist-info/LICENSE
isort_black_compat-4.3.211.dist-info/METADATA
isort_black_compat-4.3.211.dist-info/WHEEL
isort_black_compat-4.3.211.dist-info/entry_points.txt
isort_black_compat-4.3.211.dist-info/top_level.txt
isort_black_compat-4.3.211.dist-info/RECORD
