Metadata-Version: 2.1
Name: isort-black-compat
Version: 4.3.211
Summary: A Python utility / library to sort Python imports, written by Timothy Crosley.
Home-page: https://github.com/sshleifer/isort
Author: Sam Shleifer
Author-email: sshleifer@gmail.com
License: MIT
Keywords: Refactor,Python,Python3,Refactoring,Imports,Sort,Clean
Platform: UNKNOWN
Classifier: Development Status :: 6 - Mature
Classifier: Intended Audience :: Developers
Classifier: Natural Language :: English
Classifier: Environment :: Console
Classifier: License :: OSI Approved :: MIT License
Classifier: Programming Language :: Python
Classifier: Programming Language :: Python :: 3
Classifier: Programming Language :: Python :: 3.5
Classifier: Programming Language :: Python :: 3.6
Classifier: Programming Language :: Python :: 3.7
Classifier: Programming Language :: Python :: 3 :: Only
Classifier: Programming Language :: Python :: Implementation :: CPython
Classifier: Programming Language :: Python :: Implementation :: PyPy
Classifier: Topic :: Software Development :: Libraries
Classifier: Topic :: Utilities
Requires-Python: >=3.5
Provides-Extra: pipfile
Requires-Dist: pipreqs ; extra == 'pipfile'
Requires-Dist: requirementslib ; extra == 'pipfile'
Provides-Extra: pyproject
Requires-Dist: toml ; extra == 'pyproject'
Provides-Extra: requirements
Requires-Dist: pipreqs ; extra == 'requirements'
Requires-Dist: pip-api ; extra == 'requirements'
Provides-Extra: xdg_home
Requires-Dist: appdirs (>=1.4.0) ; extra == 'xdg_home'
